orter/__init__.py
orter/client.py
orter/context.py
orter/main.py
orter/types.py
orter/utils.py
orter/commands/analytics.py
orter/commands/chat.py
orter/commands/completions.py
orter/commands/credits.py
orter/commands/embeddings.py
orter/commands/endpoints.py
orter/commands/generation.py
orter/commands/keys.py
orter/commands/oauth.py
orter/commands/parameters.py
orter/commands/providers.py
orter/commands/raw.py
orter/commands/models/__init__.py
orter/commands/models/filters.py
orter/commands/models/formatters.py
orter/commands/models/types.py
orter-0.1.0.dist-info/METADATA
orter-0.1.0.dist-info/WHEEL
orter-0.1.0.dist-info/entry_points.txt
orter-0.1.0.dist-info/top_level.txt
orter-0.1.0.dist-info/RECORD
