Metadata-Version: 2.4
Name: orter
Version: 0.1.0
Summary: OpenRouter API CLI tool
Requires-Python: >=3.12
Requires-Dist: httpx>=0.27.2
Requires-Dist: pydantic>=2.10.0
Requires-Dist: typer>=0.21.0
